scripts/__init__.py
scripts/copyright_checker.py
scripts/copyright_template_parser.py
scripts/main.py
sny_copyright_checker-1.0.5.dist-info/licenses/LICENSE
sny_copyright_checker-1.0.5.dist-info/METADATA
sny_copyright_checker-1.0.5.dist-info/WHEEL
sny_copyright_checker-1.0.5.dist-info/entry_points.txt
sny_copyright_checker-1.0.5.dist-info/top_level.txt
sny_copyright_checker-1.0.5.dist-info/RECORD
