Metadata-Version: 2.4
Name: sny-copyright-checker
Version: 1.0.5
Summary: Pre-commit hook to check and auto-add copyright notices with multi-format and regex support
Author: SNY Group Corporation
License: MIT
Project-URL: Homepage, https://github.com/mu-triv/sny-copyright-checker
Project-URL: Repository, https://github.com/mu-triv/sny-copyright-checker
Project-URL: Issues, https://github.com/mu-triv/sny-copyright-checker/issues
Keywords: pre-commit,copyright,license,sny
Classifier: Development Status :: 4 - Beta
Classifier: Intended Audience :: Developers
Classifier: License :: OSI Approved :: MIT License
Classifier: Operating System :: OS Independent
Classifier: Programming Language :: Python :: 3
Classifier: Programming Language :: Python :: 3.10
Classifier: Programming Language :: Python :: 3.11
Classifier: Programming Language :: Python :: 3.12
Classifier: Topic :: Software Development :: Quality Assurance
Requires-Python: >=3.10
License-File: LICENSE
Requires-Dist: pathspec>=0.11.0
Provides-Extra: dev
Requires-Dist: pytest>=7.0.0; extra == "dev"
Dynamic: license-file
